flake8_loopy/__init__.py
flake8_loopy/defs.py
flake8_loopy/error_codes.py
flake8_loopy/visitor.py
flake8_loopy-1.1.0.dist-info/LICENSE
flake8_loopy-1.1.0.dist-info/METADATA
flake8_loopy-1.1.0.dist-info/WHEEL
flake8_loopy-1.1.0.dist-info/entry_points.txt
flake8_loopy-1.1.0.dist-info/top_level.txt
flake8_loopy-1.1.0.dist-info/RECORD
