Metadata-Version: 2.1
Name: flake8-loopy
Version: 1.1.0
Summary: flake8 plugin to check code quality in loops
Home-page: https://github.com/bdscharf/flake8_loopy
Author: Benjamin Scharf
Author-email: benjamin.d.scharf@gmail.com
License: MIT
Download-URL: https://github.com/bdscharf/flake8_loopy/archive/refs/tags/v1.1.0.tar.gz
Project-URL: Documentation, https://github.com/bdscharf/flake8_loopy/blob/main/README.md
Project-URL: Source, https://github.com/bdscharf/flake8_loopy
Project-URL: Tracker, https://github.com/bdscharf/flake8_loopy/issues
Keywords: flake8
Platform: UNKNOWN
Classifier: Framework :: Flake8
Classifier: Intended Audience :: Developers
Classifier: License :: OSI Approved :: MIT License
Classifier: Operating System :: OS Independent
Classifier: Programming Language :: Python
Classifier: Programming Language :: Python :: 3
Classifier: Topic :: Software Development :: Libraries :: Python Modules
Classifier: Topic :: Software Development :: Quality Assurance
License-File: LICENSE
Requires-Dist: flake8 (>=3.0.0)
